[
	{
	  "id": 1,
	  "firstName": "John",
	  "lastName": "Lenes",
	  "age": 42,
	  "race": "African American",
	  "sex": "M",
	  "dob": "09/12/1982",
	  "height": "5'10\"",
	  "address": "3672 Whispymound Drive, Vinewood Hills",
	  "aptNumber": "N/A",
	  "phoneNumber": "(555) 987-6543",
	  "driversLicenseNumber": "L543210",
	  "driversLicenseConfirmationNumber": "12345678",
	  "isDriversLicenseValid": true,
	  "driversLicenseReason": "N/A",
	  "driversLicenseIssue": "05/18/2010",
	  "driversLicenseExp": "05/18/2025",
	  "driversLicenseClass": "B",
	  "isDriversLicenseCommercial": false,
	  "isDonor": false,
	  "hasFirearmLicense": false,
	  "isFirearmLicenseValid": false,
	  "firearmLicenseReason": "N/A",
	  "firearmLicenseType": "N/A",
	  "registeredVehicle": "02J16478",
	  "events": [
		{
		  "eventName": "TRAFFIC TICKET",
		  "eventDescription": "Issued a ticket for speeding on Del Perro Freeway. 07/03/2019.",
		  "eventID": 1
		},
		{
		  "eventName": "VERBAL WARNING",
		  "eventDescription": "Received a verbal warning for reckless driving on Eclipse Boulevard. 12/20/2022.",
		  "eventID": 2
		}
	  ],
	  "warrants": [
		{
		  "warrantType": "HRAW",
		  "warrantTitle": "ASSAULT",
		  "warrantDetails": "High-risk arrest warrant issued by JUDGE LUCAS W. HARRIS for the crime of ASSAULT. Suspect is considered dangerous.",
		  "warrantID": 1
		}
	  ]
	},
	{
	  "id": 2,
	  "firstName": "Frank",
	  "lastName": "Rodriguez",
	  "age": 28,
	  "race": "Hispanic",
	  "sex": "M",
	  "dob": "03/08/1996",
	  "height": "6'2\"",
	  "address": "1892 Marathon Avenue, Sandy Shores",
	  "aptNumber": "Apt 3B",
	  "phoneNumber": "(555) 789-0123",
	  "driversLicenseNumber": "L876543",
	  "driversLicenseConfirmationNumber": "87654321",
	  "isDriversLicenseValid": true,
	  "driversLicenseReason": "N/A",
	  "driversLicenseIssue": "02/14/2012",
	  "driversLicenseExp": "02/14/2027",
	  "driversLicenseClass": "C",
	  "isDriversLicenseCommercial": false,
	  "isDonor": true,
	  "hasFirearmLicense": false,
	  "isFirearmLicenseValid": false,
	  "firearmLicenseReason": "N/A",
	  "firearmLicenseType": "N/A",
	  "registeredVehicle": "9F291874",
	  "events": [
		{
		  "eventName": "TRAFFIC TICKET",
		  "eventDescription": "Received a ticket for running a red light on Joshua Road. 09/30/2023.",
		  "eventID": 1
		}
	  ],
	  "warrants": []
	},
	{
	  "id": 3,
	  "firstName": "James",
	  "lastName": "Clark",
	  "age": 39,
	  "race": "Caucasian",
	  "sex": "M",
	  "dob": "11/20/1985",
	  "height": "5'11\"",
	  "address": "2283 Didion Drive, Rockford Hills",
	  "aptNumber": "N/A",
	  "phoneNumber": "(555) 234-5678",
	  "driversLicenseNumber": "L432109",
	  "driversLicenseConfirmationNumber": "98765432",
	  "isDriversLicenseValid": false,
	  "driversLicenseReason": "EXPIRED",
	  "driversLicenseIssue": "03/15/2007",
	  "driversLicenseExp": "03/15/2023",
	  "driversLicenseClass": "A",
	  "isDriversLicenseCommercial": true,
	  "isDonor": false,
	  "hasFirearmLicense": false,
	  "isFirearmLicenseValid": false,
	  "firearmLicenseReason": "N/A",
	  "firearmLicenseType": "N/A",
	  "registeredVehicle": "3C682055",
	  "events": [
		{
		  "eventName": "TRAFFIC TICKET",
		  "eventDescription": "Issued a ticket for expired registration on Power Street. 05/07/2022.",
		  "eventID": 1
		},
		{
		  "eventName": "VERBAL WARNING",
		  "eventDescription": "Received a verbal warning for failure to yield on Integrity Way. 11/14/2023.",
		  "eventID": 2
		}
	  ],
	  "warrants": [
		{
		  "warrantType": "LRAW",
		  "warrantTitle": "FRAUD",
		  "warrantDetails": "Low-risk arrest warrant issued by JUDGE EMMA R. GARCIA for the crime of FRAUD. Suspect is to be detained.",
		  "warrantID": 1
		}
	  ]
	},
	{
	  "id": 4,
	  "firstName": "Robert",
	  "lastName": "Martinez",
	  "age": 45,
	  "race": "Hispanic",
	  "sex": "M",
	  "dob": "07/17/1979",
	  "height": "6'0\"",
	  "address": "4512 Grove Street, Davis",
	  "aptNumber": "N/A",
	  "phoneNumber": "(555) 345-6789",
	  "driversLicenseNumber": "L654321",
	  "driversLicenseConfirmationNumber": "54321678",
	  "isDriversLicenseValid": true,
	  "driversLicenseReason": "N/A",
	  "driversLicenseIssue": "08/22/2000",
	  "driversLicenseExp": "08/22/2025",
	  "driversLicenseClass": "C",
	  "isDriversLicenseCommercial": false,
	  "isDonor": true,
	  "hasFirearmLicense": false,
	  "isFirearmLicenseValid": false,
	  "firearmLicenseReason": "N/A",
	  "firearmLicenseType": "N/A",
	  "registeredVehicle": "5H820309",
	  "events": [],
	  "warrants": []
	},
	{
	  "id": 5,
	  "firstName": "David",
	  "lastName": "Gonzalez",
	  "age": 31,
	  "race": "Hispanic",
	  "sex": "M",
	  "dob": "12/03/1993",
	  "height": "5'9\"",
	  "address": "768 Mad Wayne Thunder Drive, Vinewood",
	  "aptNumber": "N/A",
	  "phoneNumber": "(555) 456-7890",
	  "driversLicenseNumber": "L321098",
	  "driversLicenseConfirmationNumber": "43218765",
	  "isDriversLicenseValid": true,
	  "driversLicenseReason": "N/A",
	  "driversLicenseIssue": "10/05/2010",
	  "driversLicenseExp": "10/05/2025",
	  "driversLicenseClass": "B",
	  "isDriversLicenseCommercial": false,
	  "isDonor": false,
	  "hasFirearmLicense": false,
	  "isFirearmLicenseValid": false,
	  "firearmLicenseReason": "N/A",
	  "firearmLicenseType": "N/A",
	  "registeredVehicle": "9K164872",
	  "events": [
		{
		  "eventName": "TRAFFIC TICKET",
		  "eventDescription": "Issued a ticket for illegal parking on Prosperity Street. 02/20/2022.",
		  "eventID": 1
		}
	  ],
	  "warrants": []
	},
  {
    "id": 6,
    "firstName": "Michael",
    "lastName": "Ramirez",
    "age": 35,
    "race": "Caucasian",
    "sex": "M",
    "dob": "02/15/1989",
    "height": "5'11\"",
    "address": "2647 Paleto Boulevard, Paleto Bay",
    "aptNumber": "Apt 2C",
    "phoneNumber": "(555) 876-5432",
    "driversLicenseNumber": "L987654",
    "driversLicenseConfirmationNumber": "76543219",
    "isDriversLicenseValid": true,
    "driversLicenseReason": "N/A",
    "driversLicenseIssue": "04/10/2013",
    "driversLicenseExp": "04/10/2028",
    "driversLicenseClass": "B",
    "isDriversLicenseCommercial": false,
    "isDonor": true,
    "hasFirearmLicense": false,
    "isFirearmLicenseValid": false,
    "firearmLicenseReason": "N/A",
    "firearmLicenseType": "N/A",
    "registeredVehicle": "4G971263",
    "events": [
      {
        "eventName": "TRAFFIC TICKET",
        "eventDescription": "Received a ticket for failure to stop at a stop sign on Paleto Boulevard. 06/05/2023.",
        "eventID": 1
      }
    ],
    "warrants": []
  },
  {
    "id": 7,
    "firstName": "Daniel",
    "lastName": "Perez",
    "age": 29,
    "race": "Hispanic",
    "sex": "M",
    "dob": "10/27/1995",
    "height": "5'10\"",
    "address": "1298 Mirror Park Boulevard, Mirror Park",
    "aptNumber": "N/A",
    "phoneNumber": "(555) 765-4321",
    "driversLicenseNumber": "L876543",
    "driversLicenseConfirmationNumber": "65432187",
    "isDriversLicenseValid": true,
    "driversLicenseReason": "N/A",
    "driversLicenseIssue": "12/18/2011",
    "driversLicenseExp": "12/18/2026",
    "driversLicenseClass": "B",
    "isDriversLicenseCommercial": false,
    "isDonor": false,
    "hasFirearmLicense": false,
    "isFirearmLicenseValid": false,
    "firearmLicenseReason": "N/A",
    "firearmLicenseType": "N/A",
    "registeredVehicle": "7E682304",
    "events": [
      {
        "eventName": "TRAFFIC TICKET",
        "eventDescription": "Received a ticket for speeding on Mirror Park Boulevard. 08/12/2023.",
        "eventID": 1
      }
    ],
    "warrants": []
  },
  {
    "id": 8,
    "firstName": "Christopher",
    "lastName": "Flores",
    "age": 41,
    "race": "Hispanic",
    "sex": "M",
    "dob": "06/11/1983",
    "height": "6'1\"",
    "address": "1853 Elgin Avenue, South Los Santos",
    "aptNumber": "N/A",
    "phoneNumber": "(555) 654-3210",
    "driversLicenseNumber": "L765432",
    "driversLicenseConfirmationNumber": "54321876",
    "isDriversLicenseValid": true,
    "driversLicenseReason": "N/A",
    "driversLicenseIssue": "03/24/2009",
    "driversLicenseExp": "03/24/2024",
    "driversLicenseClass": "B",
    "isDriversLicenseCommercial": false,
    "isDonor": true,
    "hasFirearmLicense": true,
    "isFirearmLicenseValid": true,
    "firearmLicenseReason": "Valid CCW Holder",
    "firearmLicenseType": "CCW",
    "registeredVehicle": "8K164832",
    "events": [],
    "warrants": []
  },
  {
    "id": 9,
    "firstName": "Matthew",
    "lastName": "Garcia",
    "age": 37,
    "race": "Hispanic",
    "sex": "M",
    "dob": "08/29/1987",
    "height": "5'9\"",
    "address": "763 Forum Drive, Mission Row",
    "aptNumber": "Suite 501",
    "phoneNumber": "(555) 543-2109",
    "driversLicenseNumber": "L654321",
    "driversLicenseConfirmationNumber": "43217654",
    "isDriversLicenseValid": true,
    "driversLicenseReason": "N/A",
    "driversLicenseIssue": "07/15/2012",
    "driversLicenseExp": "07/15/2027",
    "driversLicenseClass": "B",
    "isDriversLicenseCommercial": false,
    "isDonor": true,
    "hasFirearmLicense": false,
    "isFirearmLicenseValid": false,
    "firearmLicenseReason": "N/A",
    "firearmLicenseType": "N/A",
    "registeredVehicle": "2F682710",
    "events": [],
    "warrants": []
  },
  {
    "id": 10,
    "firstName": "Andrew",
    "lastName": "Martinez",
    "age": 33,
    "race": "Caucasian",
    "sex": "M",
    "dob": "05/14/1991",
    "height": "6'0\"",
    "address": "3928 Roy Lowenstein Boulevard, Pillbox Hill",
    "aptNumber": "Suite 1201",
    "phoneNumber": "(555) 432-1098",
    "driversLicenseNumber": "L543210",
    "driversLicenseConfirmationNumber": "32109876",
    "isDriversLicenseValid": true,
    "driversLicenseReason": "N/A",
    "driversLicenseIssue": "09/23/2013",
    "driversLicenseExp": "09/23/2028",
    "driversLicenseClass": "B",
    "isDriversLicenseCommercial": false,
    "isDonor": false,
    "hasFirearmLicense": false,
    "isFirearmLicenseValid": false,
    "firearmLicenseReason": "N/A",
    "firearmLicenseType": "N/A",
    "registeredVehicle": "1K820369",
    "events": [],
    "warrants": []
  },
  {
    "id": 11,
    "firstName": "Joshua",
    "lastName": "Hernandez",
    "age": 30,
    "race": "Hispanic",
    "sex": "M",
    "dob": "09/08/1994",
    "height": "5'8\"",
    "address": "6395 Grove Street, Davis",
    "aptNumber": "N/A",
    "phoneNumber": "(555) 321-0987",
    "driversLicenseNumber": "L432109",
    "driversLicenseConfirmationNumber": "32109876",
    "isDriversLicenseValid": true,
    "driversLicenseReason": "N/A",
    "driversLicenseIssue": "10/17/2010",
    "driversLicenseExp": "10/17/2025",
    "driversLicenseClass": "B",
    "isDriversLicenseCommercial": false,
    "isDonor": false,
    "hasFirearmLicense": false,
    "isFirearmLicenseValid": false,
    "firearmLicenseReason": "N/A",
    "firearmLicenseType": "N/A",
    "registeredVehicle": "8H820372",
    "events": [
      {
        "eventName": "TRAFFIC TICKET",
        "eventDescription": "Issued a ticket for illegal U-turn on Grove Street. 01/05/2023.",
        "eventID": 1
      }
    ],
    "warrants": []
  },
  {
    "id": 12,
    "firstName": "Brandon",
    "lastName": "Lopez",
    "age": 26,
    "race": "Hispanic",
    "sex": "M",
    "dob": "06/30/1998",
    "height": "5'10\"",
    "address": "8752 Exceptionalists Way, Los Santos International Airport",
    "aptNumber": "N/A",
    "phoneNumber": "(555) 432-7654",
    "driversLicenseNumber": "L321098",
    "driversLicenseConfirmationNumber": "21098765",
    "isDriversLicenseValid": true,
    "driversLicenseReason": "N/A",
    "driversLicenseIssue": "11/25/2014",
    "driversLicenseExp": "11/25/2029",
    "driversLicenseClass": "B",
    "isDriversLicenseCommercial": false,
    "isDonor": false,
    "hasFirearmLicense": false,
    "isFirearmLicenseValid": false,
    "firearmLicenseReason": "N/A",
    "firearmLicenseType": "N/A",
    "registeredVehicle": "2K164831",
    "events": [
      {
        "eventName": "TRAFFIC TICKET",
        "eventDescription": "Issued a ticket for expired registration on Exceptionalists Way. 03/20/2023.",
        "eventID": 1
      }
    ],
    "warrants": []
  },
  {
    "id": 13,
    "firstName": "Tyler",
    "lastName": "Gonzalez",
    "age": 34,
    "race": "Hispanic",
    "sex": "M",
    "dob": "04/12/1990",
    "height": "5'11\"",
    "address": "2987 Bay City Avenue, Del Perro",
    "aptNumber": "N/A",
    "phoneNumber": "(555) 765-4321",
    "driversLicenseNumber": "L098765",
    "driversLicenseConfirmationNumber": "98765432",
    "isDriversLicenseValid": true,
    "driversLicenseReason": "N/A",
    "driversLicenseIssue": "08/05/2013",
    "driversLicenseExp": "08/05/2028",
    "driversLicenseClass": "B",
    "isDriversLicenseCommercial": false,
    "isDonor": true,
    "hasFirearmLicense": false,
    "isFirearmLicenseValid": false,
    "firearmLicenseReason": "N/A",
    "firearmLicenseType": "N/A",
    "registeredVehicle": "4H682943",
    "events": [],
    "warrants": []
  },
  {
    "id": 14,
    "firstName": "Ryan",
    "lastName": "Hernandez",
    "age": 27,
    "race": "Hispanic",
    "sex": "M",
    "dob": "03/19/1997",
    "height": "5'9\"",
    "address": "763 Popular Street, Little Seoul",
    "aptNumber": "N/A",
    "phoneNumber": "(555) 543-2198",
    "driversLicenseNumber": "L987654",
    "driversLicenseConfirmationNumber": "87654321",
    "isDriversLicenseValid": true,
    "driversLicenseReason": "N/A",
    "driversLicenseIssue": "12/20/2011",
    "driversLicenseExp": "12/20/2026",
    "driversLicenseClass": "B",
    "isDriversLicenseCommercial": false,
    "isDonor": true,
    "hasFirearmLicense": false,
    "isFirearmLicenseValid": false,
    "firearmLicenseReason": "N/A",
    "firearmLicenseType": "N/A",
    "registeredVehicle": "9J164823",
    "events": [
      {
        "eventName": "TRAFFIC TICKET",
        "eventDescription": "Issued a ticket for expired registration on Popular Street. 04/10/2023.",
        "eventID": 1
      }
    ],
    "warrants": []
  },
  {
    "id": 15,
    "firstName": "Jacob",
    "lastName": "Sanchez",
    "age": 32,
    "race": "Hispanic",
    "sex": "M",
    "dob": "11/25/1992",
    "height": "5'10\"",
    "address": "5832 Amarillo Vista, La Mesa",
    "aptNumber": "Apt 501",
    "phoneNumber": "(555) 432-1098",
    "driversLicenseNumber": "L876543",
    "driversLicenseConfirmationNumber": "76543219",
    "isDriversLicenseValid": true,
    "driversLicenseReason": "N/A",
    "driversLicenseIssue": "02/28/2012",
    "driversLicenseExp": "02/28/2027",
    "driversLicenseClass": "B",
    "isDriversLicenseCommercial": false,
    "isDonor": false,
    "hasFirearmLicense": false,
    "isFirearmLicenseValid": false,
    "firearmLicenseReason": "N/A",
    "firearmLicenseType": "N/A",
    "registeredVehicle": "6G820130",
    "events": [
      {
        "eventName": "TRAFFIC TICKET",
        "eventDescription": "Issued a ticket for failure to signal on Amarillo Vista. 07/15/2023.",
        "eventID": 1
      }
    ],
    "warrants": []
  },
  {
    "id": 16,
    "firstName": "Ethan",
    "lastName": "Torres",
    "age": 29,
    "race": "Hispanic",
    "sex": "M",
    "dob": "08/14/1995",
    "height": "5'11\"",
    "address": "4925 Vespucci Boulevard, Vespucci Canals",
    "aptNumber": "Suite 201",
    "phoneNumber": "(555) 765-4321",
    "driversLicenseNumber": "L765432",
    "driversLicenseConfirmationNumber": "65432187",
    "isDriversLicenseValid": true,
    "driversLicenseReason": "N/A",
    "driversLicenseIssue": "10/20/2011",
    "driversLicenseExp": "10/20/2026",
    "driversLicenseClass": "B",
    "isDriversLicenseCommercial": false,
    "isDonor": false,
    "hasFirearmLicense": false,
    "isFirearmLicenseValid": false,
    "firearmLicenseReason": "N/A",
    "firearmLicenseType": "N/A",
    "registeredVehicle": "7F682317",
    "events": [],
    "warrants": []
  },
  {
    "id": 17,
    "firstName": "Aiden",
    "lastName": "Reyes",
    "age": 31,
    "race": "Hispanic",
    "sex": "M",
    "dob": "05/02/1993",
    "height": "6'0\"",
    "address": "6432 Little Bighorn Avenue, Rancho",
    "aptNumber": "N/A",
    "phoneNumber": "(555) 432-1098",
    "driversLicenseNumber": "L543210",
    "driversLicenseConfirmationNumber": "43210987",
    "isDriversLicenseValid": true,
    "driversLicenseReason": "N/A",
    "driversLicenseIssue": "09/18/2010",
    "driversLicenseExp": "09/18/2025",
    "driversLicenseClass": "B",
    "isDriversLicenseCommercial": false,
    "isDonor": true,
    "hasFirearmLicense": false,
    "isFirearmLicenseValid": false,
    "firearmLicenseReason": "N/A",
    "firearmLicenseType": "N/A",
    "registeredVehicle": "1K820497",
    "events": [
      {
        "eventName": "TRAFFIC TICKET",
        "eventDescription": "Issued a ticket for expired registration on Little Bighorn Avenue. 06/12/2022.",
        "eventID": 1
      }
    ],
    "warrants": []
  },
  {
    "id": 18,
    "firstName": "Noah",
    "lastName": "Cruz",
    "age": 36,
    "race": "Hispanic",
    "sex": "M",
    "dob": "09/30/1988",
    "height": "5'10\"",
    "address": "8372 San Andreas Avenue, El Burro Heights",
    "aptNumber": "Apt 301",
    "phoneNumber": "(555) 543-2198",
    "driversLicenseNumber": "L432109",
    "driversLicenseConfirmationNumber": "32109876",
    "isDriversLicenseValid": true,
    "driversLicenseReason": "N/A",
    "driversLicenseIssue": "11/24/2013",
    "driversLicenseExp": "11/24/2028",
    "driversLicenseClass": "B",
    "isDriversLicenseCommercial": false,
    "isDonor": true,
    "hasFirearmLicense": false,
    "isFirearmLicenseValid": false,
    "firearmLicenseReason": "N/A",
    "firearmLicenseType": "N/A",
    "registeredVehicle": "5F682720",
    "events": [
      {
        "eventName": "TRAFFIC TICKET",
        "eventDescription": "Issued a ticket for speeding on San Andreas Avenue. 01/10/2023.",
        "eventID": 1
      }
    ],
    "warrants": []
  },
  {
    "id": 19,
    "firstName": "Logan",
    "lastName": "Gutierrez",
    "age": 33,
    "race": "Hispanic",
    "sex": "M",
    "dob": "12/26/1991",
    "height": "5'9\"",
    "address": "2981 Vinewood Park Drive, Vinewood Hills",
    "aptNumber": "N/A",
    "phoneNumber": "(555) 321-0987",
    "driversLicenseNumber": "L321098",
    "driversLicenseConfirmationNumber": "21098765",
    "isDriversLicenseValid": true,
    "driversLicenseReason": "N/A",
    "driversLicenseIssue": "02/15/2012",
    "driversLicenseExp": "02/15/2027",
    "driversLicenseClass": "B",
    "isDriversLicenseCommercial": false,
    "isDonor": false,
    "hasFirearmLicense": false,
    "isFirearmLicenseValid": false,
    "firearmLicenseReason": "N/A",
    "firearmLicenseType": "N/A",
    "registeredVehicle": "8J164819",
    "events": [
      {
        "eventName": "TRAFFIC TICKET",
        "eventDescription": "Issued a ticket for illegal parking on Vinewood Park Drive. 03/05/2023.",
        "eventID": 1
      }
    ],
    "warrants": []
  },
  {
    "id": 20,
    "firstName": "Lucas",
    "lastName": "Ruiz",
    "age": 28,
    "race": "Hispanic",
    "sex": "M",
    "dob": "07/09/1996",
    "height": "5'11\"",
    "address": "9834 Las Lagunas Boulevard, La Puerta",
    "aptNumber": "N/A",
    "phoneNumber": "(555) 654-3210",
    "driversLicenseNumber": "L098765",
    "driversLicenseConfirmationNumber": "98765432",
    "isDriversLicenseValid": true,
    "driversLicenseReason": "N/A",
    "driversLicenseIssue": "09/02/2013",
    "driversLicenseExp": "09/02/2028",
    "driversLicenseClass": "B",
    "isDriversLicenseCommercial": false,
    "isDonor": false,
    "hasFirearmLicense": false,
    "isFirearmLicenseValid": false,
    "firearmLicenseReason": "N/A",
    "firearmLicenseType": "N/A",
    "registeredVehicle": "2K820317",
    "events": [],
    "warrants": []
  },
  {
    "id": 21,
    "firstName": "Elijah",
    "lastName": "Gomez",
    "age": 30,
    "race": "Hispanic",
    "sex": "M",
    "dob": "06/15/1994",
    "height": "6'0\"",
    "address": "5723 Grove Street, Davis",
    "aptNumber": "N/A",
    "phoneNumber": "(555) 543-8765",
    "driversLicenseNumber": "L543210",
    "driversLicenseConfirmationNumber": "43210987",
    "isDriversLicenseValid": true,
    "driversLicenseReason": "N/A",
    "driversLicenseIssue": "08/18/2010",
    "driversLicenseExp": "08/18/2025",
    "driversLicenseClass": "B",
    "isDriversLicenseCommercial": false,
    "isDonor": false,
    "hasFirearmLicense": false,
    "isFirearmLicenseValid": false,
    "firearmLicenseReason": "N/A",
    "firearmLicenseType": "N/A",
    "registeredVehicle": "4J164829",
    "events": [
      {
        "eventName": "TRAFFIC TICKET",
        "eventDescription": "Issued a ticket for expired registration on Grove Street. 02/12/2023.",
        "eventID": 1
      }
    ],
    "warrants": []
  },
  {
    "id": 22,
    "firstName": "Oliver",
    "lastName": "Torres",
    "age": 35,
    "race": "Hispanic",
    "sex": "M",
    "dob": "10/29/1989",
    "height": "5'10\"",
    "address": "9281 Forum Drive, West Vinewood",
    "aptNumber": "N/A",
    "phoneNumber": "(555) 678-9012",
    "driversLicenseNumber": "L765432",
    "driversLicenseConfirmationNumber": "65432187",
    "isDriversLicenseValid": true,
    "driversLicenseReason": "N/A",
    "driversLicenseIssue": "12/10/2013",
    "driversLicenseExp": "12/10/2028",
    "driversLicenseClass": "B",
    "isDriversLicenseCommercial": false,
    "isDonor": true,
    "hasFirearmLicense": false,
    "isFirearmLicenseValid": false,
    "firearmLicenseReason": "N/A",
    "firearmLicenseType": "N/A",
    "registeredVehicle": "5F682111",
    "events": [
      {
        "eventName": "TRAFFIC TICKET",
        "eventDescription": "Issued a ticket for running a red light on Forum Drive. 03/22/2023.",
        "eventID": 1
      }
    ],
    "warrants": []
  },
  {
    "id": 23,
    "firstName": "Levi",
    "lastName": "Gutierrez",
    "age": 29,
    "race": "Hispanic",
    "sex": "M",
    "dob": "05/18/1995",
    "height": "5'9\"",
    "address": "6214 Eclipse Boulevard, Vinewood Hills",
    "aptNumber": "N/A",
    "phoneNumber": "(555) 890-1234",
    "driversLicenseNumber": "L432109",
    "driversLicenseConfirmationNumber": "32109876",
    "isDriversLicenseValid": true,
    "driversLicenseReason": "N/A",
    "driversLicenseIssue": "06/30/2011",
    "driversLicenseExp": "06/30/2026",
    "driversLicenseClass": "B",
    "isDriversLicenseCommercial": false,
    "isDonor": false,
    "hasFirearmLicense": false,
    "isFirearmLicenseValid": false,
    "firearmLicenseReason": "N/A",
    "firearmLicenseType": "N/A",
    "registeredVehicle": "8J164511",
    "events": [],
    "warrants": []
  },
  {
    "id": 24,
    "firstName": "Jack",
    "lastName": "Ruiz",
    "age": 33,
    "race": "Hispanic",
    "sex": "M",
    "dob": "09/09/1991",
    "height": "5'11\"",
    "address": "4523 Mad Wayne Thunder Drive, Vinewood",
    "aptNumber": "N/A",
    "phoneNumber": "(555) 432-9876",
    "driversLicenseNumber": "L321098",
    "driversLicenseConfirmationNumber": "21098765",
    "isDriversLicenseValid": true,
    "driversLicenseReason": "N/A",
    "driversLicenseIssue": "11/10/2011",
    "driversLicenseExp": "11/10/2026",
    "driversLicenseClass": "B",
    "isDriversLicenseCommercial": false,
    "isDonor": false,
    "hasFirearmLicense": false,
    "isFirearmLicenseValid": false,
    "firearmLicenseReason": "N/A",
    "firearmLicenseType": "N/A",
    "registeredVehicle": "9K164843",
    "events": [],
    "warrants": []
  },
  {
    "id": 25,
    "firstName": "Mason",
    "lastName": "Ramirez",
    "age": 28,
    "race": "Hispanic",
    "sex": "M",
    "dob": "04/25/1996",
    "height": "6'1\"",
    "address": "7982 Alta Street, Vinewood Hills",
    "aptNumber": "N/A",
    "phoneNumber": "(555) 543-8765",
    "driversLicenseNumber": "L098765",
    "driversLicenseConfirmationNumber": "98765432",
    "isDriversLicenseValid": true,
    "driversLicenseReason": "N/A",
    "driversLicenseIssue": "06/08/2013",
    "driversLicenseExp": "06/08/2028",
    "driversLicenseClass": "B",
    "isDriversLicenseCommercial": false,
    "isDonor": false,
    "hasFirearmLicense": false,
    "isFirearmLicenseValid": false,
    "firearmLicenseReason": "N/A",
    "firearmLicenseType": "N/A",
    "registeredVehicle": "4J164819",
    "events": [],
    "warrants": []
  },
	{
	  "id": 26,
	  "firstName": "Emily",
	  "lastName": "Taylor",
	  "age": 29,
	  "race": "Caucasian",
	  "sex": "F",
	  "dob": "06/15/1995",
	  "height": "5'6\"",
	  "address": "432 Vespucci Boulevard, Vespucci Canals",
	  "aptNumber": "Apt 2B",
	  "phoneNumber": "(555) 123-4567",
	  "driversLicenseNumber": "L789012",
	  "driversLicenseConfirmationNumber": "98765432",
	  "isDriversLicenseValid": true,
	  "driversLicenseReason": "N/A",
	  "driversLicenseIssue": "04/28/2013",
	  "driversLicenseExp": "04/28/2028",
	  "driversLicenseClass": "C",
	  "isDriversLicenseCommercial": false,
	  "isDonor": false,
	  "hasFirearmLicense": false,
	  "isFirearmLicenseValid": false,
	  "firearmLicenseReason": "N/A",
	  "firearmLicenseType": "N/A",
	  "registeredVehicle": "4P123984",
	  "events": [
		{
		  "eventName": "TRAFFIC TICKET",
		  "eventDescription": "Issued a ticket for failure to stop at a stop sign on Strawberry Avenue. 09/12/2021.",
		  "eventID": 1
		},
		{
		  "eventName": "VERBAL WARNING",
		  "eventDescription": "Received a verbal warning for speeding on Elgin Avenue. 03/05/2023.",
		  "eventID": 2
		}
	  ],
	  "warrants": []
	},
	{
	  "id": 27,
	  "firstName": "Sophia",
	  "lastName": "Martinez",
	  "age": 35,
	  "race": "Hispanic",
	  "sex": "F",
	  "dob": "10/20/1989",
	  "height": "5'3\"",
	  "address": "217 Mirror Park Boulevard, Mirror Park",
	  "aptNumber": "N/A",
	  "phoneNumber": "(555) 234-5678",
	  "driversLicenseNumber": "L543210",
	  "driversLicenseConfirmationNumber": "09876543",
	  "isDriversLicenseValid": false,
	  "driversLicenseReason": "ADMINISTRATIVE SUSPENSION",
	  "driversLicenseIssue": "08/10/2010",
	  "driversLicenseExp": "08/10/2025",
	  "driversLicenseClass": "C",
	  "isDriversLicenseCommercial": false,
	  "isDonor": true,
	  "hasFirearmLicense": false,
	  "isFirearmLicenseValid": false,
	  "firearmLicenseReason": "N/A",
	  "firearmLicenseType": "N/A",
	  "registeredVehicle": "6X310282",
	  "events": [
		{
		  "eventName": "TRAFFIC TICKET",
		  "eventDescription": "Issued a ticket for driving without headlights on Eastbourne Way. 05/18/2019.",
		  "eventID": 1
		}
	  ],
	  "warrants": [
		{
		  "warrantType": "LRAW",
		  "warrantTitle": "DRUG POSSESSION",
		  "warrantDetails": "Low-risk arrest warrant issued by JUDGE SOPHIA D. THOMPSON for the crime of DRUG POSSESSION. Suspect is to be detained.",
		  "warrantID": 1
		}
	  ]
	},
	{
	  "id": 28,
	  "firstName": "Isabella",
	  "lastName": "Lopez",
	  "age": 28,
	  "race": "Hispanic",
	  "sex": "F",
	  "dob": "03/12/1996",
	  "height": "5'5\"",
	  "address": "879 Alta Place, Vinewood Hills",
	  "aptNumber": "N/A",
	  "phoneNumber": "(555) 345-6789",
	  "driversLicenseNumber": "L678901",
	  "driversLicenseConfirmationNumber": "87654321",
	  "isDriversLicenseValid": true,
	  "driversLicenseReason": "N/A",
	  "driversLicenseIssue": "12/09/2013",
	  "driversLicenseExp": "12/09/2028",
	  "driversLicenseClass": "C",
	  "isDriversLicenseCommercial": false,
	  "isDonor": false,
	  "hasFirearmLicense": false,
	  "isFirearmLicenseValid": false,
	  "firearmLicenseReason": "N/A",
	  "firearmLicenseType": "N/A",
	  "registeredVehicle": "8J172034",
	  "events": [],
	  "warrants": []
	},
	{
	  "id": 29,
	  "firstName": "Olivia",
	  "lastName": "Clark",
	  "age": 33,
	  "race": "Caucasian",
	  "sex": "F",
	  "dob": "08/04/1991",
	  "height": "5'7\"",
	  "address": "582 Prosperity Street, Morningwood",
	  "aptNumber": "Apt 4C",
	  "phoneNumber": "(555) 456-7890",
	  "driversLicenseNumber": "L901234",
	  "driversLicenseConfirmationNumber": "76543210",
	  "isDriversLicenseValid": true,
	  "driversLicenseReason": "N/A",
	  "driversLicenseIssue": "02/17/2010",
	  "driversLicenseExp": "02/17/2025",
	  "driversLicenseClass": "B",
	  "isDriversLicenseCommercial": false,
	  "isDonor": true,
	  "hasFirearmLicense": false,
	  "isFirearmLicenseValid": false,
	  "firearmLicenseReason": "N/A",
	  "firearmLicenseType": "N/A",
	  "registeredVehicle": "2R319456",
	  "events": [
		{
		  "eventName": "TRAFFIC TICKET",
		  "eventDescription": "Issued a ticket for improper lane change on Portola Drive. 11/20/2022.",
		  "eventID": 1
		}
	  ],
	  "warrants": []
	},
	{
	  "id": 30,
	  "firstName": "Emma",
	  "lastName": "Garcia",
	  "age": 26,
	  "race": "Hispanic",
	  "sex": "F",
	  "dob": "05/28/1998",
	  "height": "5'4\"",
	  "address": "1530 Bay City Avenue, Del Perro",
	  "aptNumber": "N/A",
	  "phoneNumber": "(555) 567-8901",
	  "driversLicenseNumber": "L345678",
	  "driversLicenseConfirmationNumber": "65432109",
	  "isDriversLicenseValid": true,
	  "driversLicenseReason": "N/A",
	  "driversLicenseIssue": "09/03/2014",
	  "driversLicenseExp": "09/03/2029",
	  "driversLicenseClass": "C",
	  "isDriversLicenseCommercial": false,
	  "isDonor": false,
	  "hasFirearmLicense": false,
	  "isFirearmLicenseValid": false,
	  "firearmLicenseReason": "N/A",
	  "firearmLicenseType": "N/A",
	  "registeredVehicle": "1L561093",
	  "events": [],
	  "warrants": []
	},
  {
    "id": 31,
    "firstName": "Sophia",
    "lastName": "Lopez",
    "age": 29,
    "race": "Hispanic",
    "sex": "F",
    "dob": "11/05/1995",
    "height": "5'6\"",
    "address": "4921 Strawberry Avenue, Vinewood Hills",
    "aptNumber": "N/A",
    "phoneNumber": "(555) 678-9012",
    "driversLicenseNumber": "L765432",
    "driversLicenseConfirmationNumber": "65432187",
    "isDriversLicenseValid": true,
    "driversLicenseReason": "N/A",
    "driversLicenseIssue": "12/15/2011",
    "driversLicenseExp": "12/15/2026",
    "driversLicenseClass": "B",
    "isDriversLicenseCommercial": false,
    "isDonor": true,
    "hasFirearmLicense": false,
    "isFirearmLicenseValid": false,
    "firearmLicenseReason": "N/A",
    "firearmLicenseType": "N/A",
    "registeredVehicle": "5F682130",
    "events": [
      {
        "eventName": "TRAFFIC TICKET",
        "eventDescription": "Issued a ticket for expired registration on Strawberry Avenue. 03/20/2023.",
        "eventID": 1
      }
    ],
    "warrants": []
  },
  {
    "id": 32,
    "firstName": "Isabella",
    "lastName": "Torres",
    "age": 31,
    "race": "Hispanic",
    "sex": "F",
    "dob": "08/29/1993",
    "height": "5'7\"",
    "address": "7632 Marathon Avenue, Sandy Shores",
    "aptNumber": "Apt 2C",
    "phoneNumber": "(555) 890-1234",
    "driversLicenseNumber": "L543210",
    "driversLicenseConfirmationNumber": "43210987",
    "isDriversLicenseValid": true,
    "driversLicenseReason": "N/A",
    "driversLicenseIssue": "09/12/2010",
    "driversLicenseExp": "09/12/2025",
    "driversLicenseClass": "B",
    "isDriversLicenseCommercial": false,
    "isDonor": false,
    "hasFirearmLicense": false,
    "isFirearmLicenseValid": false,
    "firearmLicenseReason": "N/A",
    "firearmLicenseType": "N/A",
    "registeredVehicle": "6K164821",
    "events": [
      {
        "eventName": "TRAFFIC TICKET",
        "eventDescription": "Issued a ticket for speeding on Marathon Avenue. 07/10/2022.",
        "eventID": 1
      }
    ],
    "warrants": []
  },
  {
    "id": 33,
    "firstName": "Charlotte",
    "lastName": "Garcia",
    "age": 28,
    "race": "Hispanic",
    "sex": "F",
    "dob": "12/21/1996",
    "height": "5'5\"",
    "address": "2983 Integrity Way, Rockford Hills",
    "aptNumber": "N/A",
    "phoneNumber": "(555) 432-1098",
    "driversLicenseNumber": "L432109",
    "driversLicenseConfirmationNumber": "32109876",
    "isDriversLicenseValid": true,
    "driversLicenseReason": "N/A",
    "driversLicenseIssue": "01/18/2012",
    "driversLicenseExp": "01/18/2027",
    "driversLicenseClass": "B",
    "isDriversLicenseCommercial": false,
    "isDonor": false,
    "hasFirearmLicense": false,
    "isFirearmLicenseValid": false,
    "firearmLicenseReason": "N/A",
    "firearmLicenseType": "N/A",
    "registeredVehicle": "9J164823",
    "events": [],
    "warrants": []
  },
  {
    "id": 34,
    "firstName": "Amelia",
    "lastName": "Martinez",
    "age": 35,
    "race": "Hispanic",
    "sex": "F",
    "dob": "09/14/1989",
    "height": "5'6\"",
    "address": "7482 Grove Street, Davis",
    "aptNumber": "N/A",
    "phoneNumber": "(555) 543-8765",
    "driversLicenseNumber": "L321098",
    "driversLicenseConfirmationNumber": "21098765",
    "isDriversLicenseValid": true,
    "driversLicenseReason": "N/A",
    "driversLicenseIssue": "11/22/2011",
    "driversLicenseExp": "11/22/2026",
    "driversLicenseClass": "B",
    "isDriversLicenseCommercial": false,
    "isDonor": true,
    "hasFirearmLicense": false,
    "isFirearmLicenseValid": false,
    "firearmLicenseReason": "N/A",
    "firearmLicenseType": "N/A",
    "registeredVehicle": "4K164829",
    "events": [],
    "warrants": []
  },
  {
    "id": 35,
    "firstName": "Mia",
    "lastName": "Ramirez",
    "age": 33,
    "race": "Hispanic",
    "sex": "F",
    "dob": "10/31/1991",
    "height": "5'7\"",
    "address": "9821 Mad Wayne Thunder Drive, Vinewood",
    "aptNumber": "N/A",
    "phoneNumber": "(555) 432-9876",
    "driversLicenseNumber": "L098765",
    "driversLicenseConfirmationNumber": "98765432",
    "isDriversLicenseValid": true,
    "driversLicenseReason": "N/A",
    "driversLicenseIssue": "12/04/2011",
    "driversLicenseExp": "12/04/2026",
    "driversLicenseClass": "B",
    "isDriversLicenseCommercial": false,
    "isDonor": false,
    "hasFirearmLicense": false,
    "isFirearmLicenseValid": false,
    "firearmLicenseReason": "N/A",
    "firearmLicenseType": "N/A",
    "registeredVehicle": "5K164819",
    "events": [],
    "warrants": []
  },
   {
    "id": 36,
    "firstName": "Harper",
    "lastName": "Ruiz",
    "age": 27,
    "race": "Hispanic",
    "sex": "F",
    "dob": "05/07/1997",
    "height": "5'5\"",
    "address": "6723 Las Lagunas Boulevard, La Puerta",
    "aptNumber": "N/A",
    "phoneNumber": "(555) 543-2109",
    "driversLicenseNumber": "L543210",
    "driversLicenseConfirmationNumber": "43210987",
    "isDriversLicenseValid": true,
    "driversLicenseReason": "N/A",
    "driversLicenseIssue": "07/20/2013",
    "driversLicenseExp": "07/20/2028",
    "driversLicenseClass": "B",
    "isDriversLicenseCommercial": false,
    "isDonor": true,
    "hasFirearmLicense": false,
    "isFirearmLicenseValid": false,
    "firearmLicenseReason": "N/A",
    "firearmLicenseType": "N/A",
    "registeredVehicle": "6F682139",
    "events": [],
    "warrants": []
  },
  {
    "id": 37,
    "firstName": "Evelyn",
    "lastName": "Gutierrez",
    "age": 30,
    "race": "Hispanic",
    "sex": "F",
    "dob": "02/16/1994",
    "height": "5'4\"",
    "address": "1982 Alta Street, Vinewood Hills",
    "aptNumber": "N/A",
    "phoneNumber": "(555) 890-9876",
    "driversLicenseNumber": "L321098",
    "driversLicenseConfirmationNumber": "21098765",
    "isDriversLicenseValid": true,
    "driversLicenseReason": "N/A",
    "driversLicenseIssue": "03/29/2011",
    "driversLicenseExp": "03/29/2026",
    "driversLicenseClass": "B",
    "isDriversLicenseCommercial": false,
    "isDonor": false,
    "hasFirearmLicense": false,
    "isFirearmLicenseValid": false,
    "firearmLicenseReason": "N/A",
    "firearmLicenseType": "N/A",
    "registeredVehicle": "7J164823",
    "events": [],
    "warrants": []
  },
  {
    "id": 38,
    "firstName": "Aria",
    "lastName": "Martinez",
    "age": 26,
    "race": "Hispanic",
    "sex": "F",
    "dob": "09/29/1998",
    "height": "5'6\"",
    "address": "5421 Eclipse Boulevard, Vinewood Hills",
    "aptNumber": "N/A",
    "phoneNumber": "(555) 678-5432",
    "driversLicenseNumber": "L432109",
    "driversLicenseConfirmationNumber": "32109876",
    "isDriversLicenseValid": true,
    "driversLicenseReason": "N/A",
    "driversLicenseIssue": "10/14/2014",
    "driversLicenseExp": "10/14/2029",
    "driversLicenseClass": "B",
    "isDriversLicenseCommercial": false,
    "isDonor": true,
    "hasFirearmLicense": false,
    "isFirearmLicenseValid": false,
    "firearmLicenseReason": "N/A",
    "firearmLicenseType": "N/A",
    "registeredVehicle": "8K164821",
    "events": [],
    "warrants": []
  },
  {
    "id": 39,
    "firstName": "Scarlett",
    "lastName": "Garcia",
    "age": 32,
    "race": "Hispanic",
    "sex": "F",
    "dob": "06/02/1992",
    "height": "5'5\"",
    "address": "7821 Forum Drive, West Vinewood",
    "aptNumber": "N/A",
    "phoneNumber": "(555) 432-1098",
    "driversLicenseNumber": "L543210",
    "driversLicenseConfirmationNumber": "43210987",
    "isDriversLicenseValid": true,
    "driversLicenseReason": "N/A",
    "driversLicenseIssue": "07/20/2010",
    "driversLicenseExp": "07/20/2025",
    "driversLicenseClass": "B",
    "isDriversLicenseCommercial": false,
    "isDonor": false,
    "hasFirearmLicense": false,
    "isFirearmLicenseValid": false,
    "firearmLicenseReason": "N/A",
    "firearmLicenseType": "N/A",
    "registeredVehicle": "9F682139",
    "events": [],
    "warrants": []
  },
  {
    "id": 40,
    "firstName": "Zoe",
    "lastName": "Ramirez",
    "age": 29,
    "race": "Hispanic",
    "sex": "F",
    "dob": "03/18/1995",
    "height": "5'7\"",
    "address": "6423 Power Street, Los Santos",
    "aptNumber": "N/A",
    "phoneNumber": "(555) 543-2109",
    "driversLicenseNumber": "L098765",
    "driversLicenseConfirmationNumber": "98765432",
    "isDriversLicenseValid": true,
    "driversLicenseReason": "N/A",
    "driversLicenseIssue": "04/21/2013",
    "driversLicenseExp": "04/21/2028",
    "driversLicenseClass": "B",
    "isDriversLicenseCommercial": false,
    "isDonor": false,
    "hasFirearmLicense": false,
    "isFirearmLicenseValid": false,
    "firearmLicenseReason": "N/A",
    "firearmLicenseType": "N/A",
    "registeredVehicle": "6K164819",
    "events": [],
    "warrants": []
  },
  {
    "id": 41,
    "firstName": "Emma",
    "lastName": "Smith",
    "age": 28,
    "race": "Caucasian",
    "sex": "F",
    "dob": "09/14/1996",
    "height": "5'6\"",
    "address": "4212 Milton Road, Vinewood Hills",
    "aptNumber": "Apt 301",
    "phoneNumber": "(555) 987-6543",
    "driversLicenseNumber": "L765432",
    "driversLicenseConfirmationNumber": "54321098",
    "isDriversLicenseValid": true,
    "driversLicenseReason": "N/A",
    "driversLicenseIssue": "10/30/2014",
    "driversLicenseExp": "10/30/2029",
    "driversLicenseClass": "B",
    "isDriversLicenseCommercial": false,
    "isDonor": true,
    "hasFirearmLicense": false,
    "isFirearmLicenseValid": false,
    "firearmLicenseReason": "N/A",
    "firearmLicenseType": "N/A",
    "registeredVehicle": "8P756431",
    "events": [],
    "warrants": []
  },
  {
    "id": 42,
    "firstName": "Grace",
    "lastName": "Anderson",
    "age": 31,
    "race": "Caucasian",
    "sex": "F",
    "dob": "05/08/1993",
    "height": "5'8\"",
    "address": "5101 Eclipse Boulevard, West Vinewood",
    "aptNumber": "Apt 102",
    "phoneNumber": "(555) 876-5432",
    "driversLicenseNumber": "L543210",
    "driversLicenseConfirmationNumber": "32109876",
    "isDriversLicenseValid": true,
    "driversLicenseReason": "N/A",
    "driversLicenseIssue": "06/15/2011",
    "driversLicenseExp": "06/15/2026",
    "driversLicenseClass": "B",
    "isDriversLicenseCommercial": false,
    "isDonor": true,
    "hasFirearmLicense": false,
    "isFirearmLicenseValid": false,
    "firearmLicenseReason": "N/A",
    "firearmLicenseType": "N/A",
    "registeredVehicle": "3R890127",
    "events": [],
    "warrants": []
  },
  {
    "id": 43,
    "firstName": "Olivia",
    "lastName": "Johnson",
    "age": 26,
    "race": "Caucasian",
    "sex": "F",
    "dob": "12/03/1998",
    "height": "5'4\"",
    "address": "7314 Mad Wayne Thunder Drive, Sandy Shores",
    "aptNumber": "N/A",
    "phoneNumber": "(555) 765-4321",
    "driversLicenseNumber": "L098765",
    "driversLicenseConfirmationNumber": "76543210",
    "isDriversLicenseValid": true,
    "driversLicenseReason": "N/A",
    "driversLicenseIssue": "01/20/2016",
    "driversLicenseExp": "01/20/2031",
    "driversLicenseClass": "B",
    "isDriversLicenseCommercial": false,
    "isDonor": false,
    "hasFirearmLicense": false,
    "isFirearmLicenseValid": false,
    "firearmLicenseReason": "N/A",
    "firearmLicenseType": "N/A",
    "registeredVehicle": "2T345678",
    "events": [],
    "warrants": []
  },
  {
    "id": 44,
    "firstName": "Ava",
    "lastName": "Brown",
    "age": 35,
    "race": "Caucasian",
    "sex": "F",
    "dob": "07/25/1989",
    "height": "5'7\"",
    "address": "9205 Mirror Park Boulevard, Mirror Park",
    "aptNumber": "N/A",
    "phoneNumber": "(555) 654-3210",
    "driversLicenseNumber": "L876543",
    "driversLicenseConfirmationNumber": "65432109",
    "isDriversLicenseValid": true,
    "driversLicenseReason": "N/A",
    "driversLicenseIssue": "08/12/2007",
    "driversLicenseExp": "08/12/2022",
    "driversLicenseClass": "B",
    "isDriversLicenseCommercial": false,
    "isDonor": false,
    "hasFirearmLicense": false,
    "isFirearmLicenseValid": false,
    "firearmLicenseReason": "N/A",
    "firearmLicenseType": "N/A",
    "registeredVehicle": "7G567890",
    "events": [],
    "warrants": []
  },
  {
    "id": 45,
    "firstName": "Chloe",
    "lastName": "Miller",
    "age": 30,
    "race": "Caucasian",
    "sex": "F",
    "dob": "11/11/1994",
    "height": "5'6\"",
    "address": "2837 Milton Road, Vinewood Hills",
    "aptNumber": "N/A",
    "phoneNumber": "(555) 543-2109",
    "driversLicenseNumber": "L543210",
    "driversLicenseConfirmationNumber": "43210987",
    "isDriversLicenseValid": true,
    "driversLicenseReason": "N/A",
    "driversLicenseIssue": "12/20/2012",
    "driversLicenseExp": "12/20/2027",
    "driversLicenseClass": "B",
    "isDriversLicenseCommercial": false,
    "isDonor": false,
    "hasFirearmLicense": false,
    "isFirearmLicenseValid": false,
    "firearmLicenseReason": "N/A",
    "firearmLicenseType": "N/A",
    "registeredVehicle": "4E678901",
    "events": [],
    "warrants": []
  },
   {
    "id": 46,
    "firstName": "Madison",
    "lastName": "Wilson",
    "age": 27,
    "race": "Caucasian",
    "sex": "F",
    "dob": "08/07/1997",
    "height": "5'4\"",
    "address": "5698 Bay City Avenue, Del Perro",
    "aptNumber": "Apt 205",
    "phoneNumber": "(555) 345-6789",
    "driversLicenseNumber": "L765432",
    "driversLicenseConfirmationNumber": "65432109",
    "isDriversLicenseValid": true,
    "driversLicenseReason": "N/A",
    "driversLicenseIssue": "09/25/2015",
    "driversLicenseExp": "09/25/2030",
    "driversLicenseClass": "B",
    "isDriversLicenseCommercial": false,
    "isDonor": true,
    "hasFirearmLicense": false,
    "isFirearmLicenseValid": false,
    "firearmLicenseReason": "N/A",
    "firearmLicenseType": "N/A",
    "registeredVehicle": "9B765432",
    "events": [],
    "warrants": []
  },
  {
    "id": 47,
    "firstName": "Avery",
    "lastName": "Martinez",
    "age": 33,
    "race": "Caucasian",
    "sex": "F",
    "dob": "04/30/1991",
    "height": "5'6\"",
    "address": "7391 Paleto Boulevard, Paleto Bay",
    "aptNumber": "N/A",
    "phoneNumber": "(555) 234-5678",
    "driversLicenseNumber": "L543210",
    "driversLicenseConfirmationNumber": "43210987",
    "isDriversLicenseValid": true,
    "driversLicenseReason": "N/A",
    "driversLicenseIssue": "05/15/2011",
    "driversLicenseExp": "05/15/2026",
    "driversLicenseClass": "B",
    "isDriversLicenseCommercial": false,
    "isDonor": false,
    "hasFirearmLicense": false,
    "isFirearmLicenseValid": false,
    "firearmLicenseReason": "N/A",
    "firearmLicenseType": "N/A",
    "registeredVehicle": "1C654321",
    "events": [],
    "warrants": []
  },
  {
    "id": 48,
    "firstName": "Ella",
    "lastName": "Gonzalez",
    "age": 25,
    "race": "Caucasian",
    "sex": "F",
    "dob": "11/19/1999",
    "height": "5'5\"",
    "address": "1020 Marina Drive, Pacific Bluffs",
    "aptNumber": "N/A",
    "phoneNumber": "(555) 543-2109",
    "driversLicenseNumber": "L098765",
    "driversLicenseConfirmationNumber": "87654321",
    "isDriversLicenseValid": true,
    "driversLicenseReason": "N/A",
    "driversLicenseIssue": "12/15/2017",
    "driversLicenseExp": "12/15/2032",
    "driversLicenseClass": "B",
    "isDriversLicenseCommercial": false,
    "isDonor": false,
    "hasFirearmLicense": false,
    "isFirearmLicenseValid": false,
    "firearmLicenseReason": "N/A",
    "firearmLicenseType": "N/A",
    "registeredVehicle": "4D765432",
    "events": [],
    "warrants": []
  },
  {
    "id": 49,
    "firstName": "Harper",
    "lastName": "Taylor",
    "age": 29,
    "race": "Caucasian",
    "sex": "F",
    "dob": "02/15/1995",
    "height": "5'7\"",
    "address": "8362 Baytree Canyon Road, Vinewood Hills",
    "aptNumber": "N/A",
    "phoneNumber": "(555) 432-1098",
    "driversLicenseNumber": "L543210",
    "driversLicenseConfirmationNumber": "32109876",
    "isDriversLicenseValid": true,
    "driversLicenseReason": "N/A",
    "driversLicenseIssue": "03/28/2013",
    "driversLicenseExp": "03/28/2028",
    "driversLicenseClass": "B",
    "isDriversLicenseCommercial": false,
    "isDonor": false,
    "hasFirearmLicense": false,
    "isFirearmLicenseValid": false,
    "firearmLicenseReason": "N/A",
    "firearmLicenseType": "N/A",
    "registeredVehicle": "7F654321",
    "events": [],
    "warrants": []
  },
  {
    "id": 50,
    "firstName": "Scarlett",
    "lastName": "Clark",
    "age": 32,
    "race": "Caucasian",
    "sex": "F",
    "dob": "06/02/1992",
    "height": "5'6\"",
    "address": "5102 Didion Drive, Richman Glen",
    "aptNumber": "N/A",
    "phoneNumber": "(555) 321-0987",
    "driversLicenseNumber": "L098765",
    "driversLicenseConfirmationNumber": "54321098",
    "isDriversLicenseValid": true,
    "driversLicenseReason": "N/A",
    "driversLicenseIssue": "07/20/2010",
    "driversLicenseExp": "07/20/2025",
    "driversLicenseClass": "B",
    "isDriversLicenseCommercial": false,
    "isDonor": false,
    "hasFirearmLicense": false,
    "isFirearmLicenseValid": false,
    "firearmLicenseReason": "N/A",
    "firearmLicenseType": "N/A",
    "registeredVehicle": "2A543210",
    "events": [],
    "warrants": []
  }
]